Workbook

Sheet Assumptions
A1: IVYAR Financial Model - Key Assumptions
A3: Category | B3: Assumption | C3: Year 1 | D3: Year 2 | E3: Year 3 | F3: Notes
A4: Revenue | B4: New Enterprise Clients | C4: 3 | D4: 5 | E4: 8 | F4: Number of new clients per year
A5: Revenue | B5: Avg Contract Value ($K) | C5: 200 | D5: 250 | E5: 300 | F5: Growing with upsells
A6: Revenue | B6: Annual Retention Rate | C6: 0.95 | D6: 0.96 | E6: 0.97 | F6: Government contracts sticky
A7: Revenue | B7: Expansion Revenue (%) | C7: 0.1 | D7: 0.15 | E7: 0.2 | F7: Add-on modules
A8: Revenue | B8: Transaction Fee Rate | C8: 0.02 | D8: 0.02 | E8: 0.02 | F8: 2% on procurement volume
A9: Revenue | B9: Services Revenue ($K/client) | C9: 30 | D9: 25 | E9: 20 | F9: Decreasing with maturity
A10: Costs | B10: COGS (% of Revenue) | C10: 0.25 | D10: 0.22 | E10: 0.2 | F10: Improving with scale
A11: Costs | B11: Engineering Headcount | C11: 5 | D11: 8 | E11: 12 | F11: Product development team
A12: Costs | B12: Avg Engineering Salary ($K) | C12: 120 | D12: 130 | E12: 140 | F12: Competitive compensation
A13: Costs | B13: Sales & Marketing (% Rev) | C13: 0.25 | D13: 0.2 | E13: 0.18 | F13: Efficiency improvements
A14: Costs | B14: G&A (% of Revenue) | C14: 0.15 | D14: 0.12 | E14: 0.1 | F14: Leverage from scale
A15: Costs | B15: Infrastructure ($K/month) | C15: 15 | D15: 25 | E15: 40 | F15: Cloud hosting, security
... A17: Growth | B17: Price Increase (%) | C17: 0 | D17: 0.05 | E17: 0.05 | F17: Annual price adjustment

Sheet Revenue Model
A1: IVYAR Revenue Model ($000s)
A3: Line Item | B3: Year 1 | C3: Year 2 | D3: Year 3 | E3: 3-Year Total | F3: Notes
A4: New Clients | B4: =Assumptions!C4 | C4: =Assumptions!D4 | D4: =Assumptions!E4 | E4: =SUM(B4:D4) | F4: From assumptions
A5: Retained Clients | B5: =0 | C5: =B4*Assumptions!C6 | D5: =(B4+C4)*Assumptions!D6 | E5: =SUM(B5:D5) | F5: Prior year * retention
A6: Total Clients | B6: =B4+B5 | C6: =C4+C5 | D6: =D4+D5 | E6: =D6 | F6: Cumulative active
A8: Base Subscription Revenue | B8: =B6*Assumptions!C5 | C8: =C6*Assumptions!D5 | D8: =D6*Assumptions!E5 | E8: =SUM(B8:D8) | F8: Clients * ACV
A9: Expansion Revenue | B9: =B8*Assumptions!C7 | C9: =C8*Assumptions!D7 | D9: =D8*Assumptions!E7 | E9: =SUM(B9:D9) | F9: Upsells
A10: Transaction Fees | B10: =B6*500*Assumptions!C8 | C10: =C6*750*Assumptions!D8 | D10: =D6*1000*Assumptions!E8 | E10: =SUM(B10:D10) | F10: Est. procurement vol
A11: Services Revenue | B11: =B4*Assumptions!C9 | C11: =C4*Assumptions!D9 | D11: =D4*Assumptions!E9 | E11: =SUM(B11:D11) | F11: New client impl
A13: TOTAL REVENUE | B13: =SUM(B8:B11) | C13: =SUM(C8:C11) | D13: =SUM(D8:D11) | E13: =SUM(E8:E11)

Sheet P&L Statement
A1: IVYAR Profit & Loss Statement ($000s)
A3: Line Item | B3: Year 1 | C3: Year 2 | D3: Year 3 | E3: 3-Year Total | F3: % of Rev (Y3)
A4: Revenue | B4: ='Revenue Model'!B13 | C4: ='Revenue Model'!C13 | D4: ='Revenue Model'!D13 | E4: =SUM(B4:D4) | F4: =D4/D4
A6: Cost of Goods Sold | B6: =-B4*Assumptions!C10 | C6: =-C4*Assumptions!D10 | D6: =-D4*Assumptions!E10 | E6: =SUM(B6:D6) | F6: =D6/D4
A7: GROSS PROFIT | B7: =B4+B6 | C7: =C4+C6 | D7: =D4+D6 | E7: =SUM(B7:D7) | F7: =D7/D4
A8: Gross Margin % | B8: =B7/B4 | C8: =C7/C4 | D8: =D7/D4
A10: Engineering | B10: =-Assumptions!C11*Assumptions!C12 | C10: =-Assumptions!D11*Assumptions!D12 | D10: =-Assumptions!E11*Assumptions!E12 | E10: =SUM(B10:D10) | F10: =D10/D4
A11: Sales & Marketing | B11: =-B4*Assumptions!C13 | C11: =-C4*Assumptions!D13 | D11: =-D4*Assumptions!E13 | E11: =SUM(B11:D11) | F11: =D11/D4
A12: G&A | B12: =-B4*Assumptions!C14 | C12: =-C4*Assumptions!D14 | D12: =-D4*Assumptions!E14 | E12: =SUM(B12:D12) | F12: =D12/D4
A13: Infrastructure | B13: =-Assumptions!C15*12 | C13: =-Assumptions!D15*12 | D13: =-Assumptions!E15*12 | E13: =SUM(B13:D13) | F13: =D13/D4
A14: TOTAL OPEX | B14: =SUM(B10:B13) | C14: =SUM(C10:C13) | D14: =SUM(D10:D13) | E14: =SUM(E10:E13) | F14: =D14/D4
A16: EBITDA | B16: =B7+B14 | C16: =C7+C14 | D16: =D7+D14 | E16: =SUM(B16:D16) | F16: =D16/D4
A17: EBITDA Margin % | B17: =B16/B4 | C17: =C16/C4 | D17: =D16/D4

Sheet Unit Economics
A1: IVYAR Unit Economics Analysis
A3: Metric | B3: Year 1 | C3: Year 2 | D3: Year 3
A4: Average Contract Value ($K) | B4: =Assumptions!C5 | C4: =Assumptions!D5 | D4: =Assumptions!E5
A5: Customer Acquisition Cost ($K) | B5: =-'P&L Statement'!B11/'Revenue Model'!B4 | C5: =-'P&L Statement'!C11/'Revenue Model'!C4 | D5: =-'P&L Statement'!D11/'Revenue Model'!D4
A6: Gross Margin % | B6: ='P&L Statement'!B8 | C6: ='P&L Statement'!C8 | D6: ='P&L Statement'!D8
A7: Customer Lifetime (Years) | B7: =1/(1-Assumptions!C6) | C7: =1/(1-Assumptions!D6) | D7: =1/(1-Assumptions!E6)
A8: Customer Lifetime Value ($K) | B8: =B4*B6*B7 | C8: =C4*C6*C7 | D8: =D4*D6*D7
A9: LTV:CAC Ratio | B9: =B8/B5 | C9: =C8/C5 | D9: =D8/D5
A10: CAC Payback (Months) | B10: =B5/(B4*B6/12) | C10: =C5/(C4*C6/12) | D10: =D5/(D4*D6/12)
A12: Revenue per Employee ($K) | B12: ='P&L Statement'!B4/Assumptions!C11 | C12: ='P&L Statement'!C4/Assumptions!D11 | D12: ='P&L Statement'!D4/Assumptions!E11
A13: Clients per Sales Rep (est) | B13: ='Revenue Model'!B6/2 | C13: ='Revenue Model'!C6/3 | D13: ='Revenue Model'!D6/5

Sheet Scenarios
A1: IVYAR Scenario Analysis
A3: Scenario | B3: Year 1 | C3: Year 2 | D3: Year 3 | E3: Description
A4: Conservative | B4: 500 | C4: 1000 | D4: 1500 | E4: 2 clients Y1, slower growth, lower ACV
A5: Base Case | B5: 750 | C5: 1800 | D5: 2800 | E5: 3 clients Y1, steady growth per model
A6: Optimistic | B6: 1200 | C6: 2500 | D6: 5000 | E6: 5 clients Y1, faster upsells, higher ACV

Sheet Data Room Checklist
A1: Due Diligence Data Room Structure
A3: Category | B3: Document | C3: Status | D3: Priority
A4: Corporate | B4: Certificate of Incorporation | C4: Required | D4: High
A5: Corporate | B5: Operating Agreement / Bylaws | C5: Required | D5: High
A6: Corporate | B6: Cap Table (fully diluted) | C6: Required | D6: High
A7: Corporate | B7: Board Meeting Minutes | C7: Required | D7: Medium
A8: Corporate | B8: Shareholder Agreements | C8: Required | D8: High
A9: Financial | B9: Historical Financial Statements | C9: Required | D9: High
A10: Financial | B10: Financial Model / Projections | C10: Required | D10: High
A11: Financial | B11: Bank Statements (12 months) | C11: Required | D11: Medium
A12: Financial | B12: Accounts Receivable Aging | C12: If applicable | D12: Medium
A13: Financial | B13: Tax Returns (3 years) | C13: Required | D13: High
A14: Product | B14: Product Roadmap | C14: Required | D14: High
... A29: Team | B29: Advisory Agreements | C29: If applicable | D29: Low
